{"stack_list": [{"content": [["[document]", {"style": "", "class": ""}, 0], ["html", {"style": "", "class": ""}, 0], ["body", {"class": ["home", "blog", "layout-double", "kaztag-news"], "style": ""}, 0], ["div", {"class": ["overflow-container"], "style": ""}, 0], ["div", {"class": ["max-width"], "style": ""}, 0], ["div", {"class": ["content-container"], "style": ""}, 0], ["div", {"class": ["layout-container"], "style": ""}, 0], ["section", {"class": ["main"], "style": ""}, 0], ["div", {"class": ["loop-container", "big-image-block"], "style": ""}, 0], ["div", {"class": ["post", "type-post", "double"], "style": ""}, 0], ["article", {"style": "", "class": ""}, 0], ["div", {"class": ["post-header"], "style": ""}, 0], ["meta", {"style": "", "class": ""}]], "wanted_attr": "content", "is_full_url": null, "is_non_rec_text": null, "url": "", "hash": "cefa2af8f83753d0509d18f671b5e0902d0abea914a608806e0b3523d5fcd1ef", "stack_id": "rule_c72y", "alias": ""}, {"content": [["[document]", {"style": "", "class": ""}, 0], ["html", {"style": "", "class": ""}, 0], ["body", {"class": ["home", "blog", "layout-double", "kaztag-news"], "style": ""}, 0], ["div", {"class": ["overflow-container"], "style": ""}, 0], ["div", {"class": ["max-width"], "style": ""}, 0], ["div", {"class": ["content-container"], "style": ""}, 0], ["div", {"class": ["layout-container"], "style": ""}, 0], ["section", {"class": ["main"], "style": ""}, 0], ["div", {"class": ["loop-container", "big-image-block"], "style": ""}, 0], ["div", {"class": ["post", "type-post", "double"], "style": ""}, 0], ["article", {"style": "", "class": ""}, 0], ["div", {"class": ["post-header"], "style": ""}, 0], ["h3", {"class": ["post-title"], "style": ""}]], "wanted_attr": null, "is_full_url": null, "is_non_rec_text": null, "url": "", "hash": "eb73224878305edd60320037fcc247512617fd0ba4410d2095ae9948667a9e26", "stack_id": "rule_ev3s", "alias": ""}, {"content": [["[document]", {"style": "", "class": ""}, 0], ["html", {"style": "", "class": ""}, 0], ["body", {"class": ["home", "blog", "layout-double", "kaztag-news"], "style": ""}, 0], ["div", {"class": ["overflow-container"], "style": ""}, 0], ["div", {"class": ["max-width"], "style": ""}, 0], ["div", {"class": ["content-container"], "style": ""}, 0], ["div", {"class": ["layout-container"], "style": ""}, 0], ["section", {"class": ["main"], "style": ""}, 0], ["div", {"class": ["loop-container", "big-image-block"], "style": ""}, 0], ["div", {"class": ["post", "type-post", "double"], "style": ""}, 0], ["article", {"style": "", "class": ""}, 0], ["div", {"class": ["featured-image"], "style": ""}, 0], ["a", {"style": "", "class": ""}, 0], ["img", {"class": ["attachment-medium", "size-medium"], "style": ""}]], "wanted_attr": "alt", "is_full_url": null, "is_non_rec_text": null, "url": "", "hash": "542eb242417fdb7f3630a05e197734309352dc86f0a29ef97b6eba23cd158ae4", "stack_id": "rule_qef7", "alias": ""}, {"content": [["[document]", {"style": "", "class": ""}, 0], ["html", {"style": "", "class": ""}, 0], ["body", {"class": ["home", "blog", "layout-double", "kaztag-news"], "style": ""}, 0], ["div", {"class": ["overflow-container"], "style": ""}, 0], ["div", {"class": ["max-width"], "style": ""}, 0], ["div", {"class": ["content-container"], "style": ""}, 0], ["div", {"class": ["layout-container"], "style": ""}, 0], ["section", {"class": ["main"], "style": ""}, 0], ["div", {"class": ["loop-container", "big-image-block"], "style": ""}, 0], ["div", {"class": ["post", "type-post", "double"], "style": ""}, 0], ["article", {"style": "", "class": ""}, 0], ["div", {"class": ["featured-image"], "style": ""}]], "wanted_attr": null, "is_full_url": null, "is_non_rec_text": null, "url": "", "hash": "c9de800493380d996532862fd1e6aaf974dac42159d573c85725409258b23801", "stack_id": "rule_4jau", "alias": ""}, {"content": [["[document]", {"style": "", "class": ""}, 0], ["html", {"style": "", "class": ""}, 0], ["body", {"class": ["home", "blog", "layout-double", "kaztag-news"], "style": ""}, 0], ["div", {"class": ["overflow-container"], "style": ""}, 0], ["div", {"class": ["max-width"], "style": ""}, 0], ["div", {"class": ["content-container"], "style": ""}, 0], ["div", {"class": ["layout-container"], "style": ""}, 0], ["section", {"class": ["main"], "style": ""}, 0], ["div", {"class": ["loop-container", "big-image-block"], "style": ""}, 0], ["div", {"class": ["post", "type-post", "double"], "style": ""}, 0], ["article", {"style": "", "class": ""}, 0], ["div", {"class": ["post-header"], "style": ""}, 0], ["div", {"class": ["post-byline"], "style": ""}]], "wanted_attr": null, "is_full_url": null, "is_non_rec_text": null, "url": "", "hash": "a7fce18b5952db49fdc1fc6fdb79439309854303b13972e084fd7c1ac3c83404", "stack_id": "rule_q4q1", "alias": ""}, {"content": [["[document]", {"style": "", "class": ""}, 0], ["html", {"style": "", "class": ""}, 0], ["body", {"class": ["home", "blog", "layout-double", "kaztag-news"], "style": ""}, 0], ["div", {"class": ["overflow-container"], "style": ""}, 0], ["div", {"class": ["max-width"], "style": ""}, 0], ["div", {"class": ["content-container"], "style": ""}, 0], ["div", {"class": ["layout-container"], "style": ""}, 0], ["section", {"class": ["main"], "style": ""}, 0], ["div", {"class": ["loop-container", "big-image-block"], "style": ""}, 0], ["div", {"class": ["post", "type-post", "double"], "style": ""}, 0], ["article", {"style": "", "class": ""}, 0], ["div", {"class": ["post-header"], "style": ""}, 0], ["h3", {"class": ["post-title"], "style": ""}, 0], ["a", {"style": "", "class": ""}]], "wanted_attr": "href", "is_full_url": true, "is_non_rec_text": null, "url": "https://kaztag.kz/en/news/?PAGEN_1=1", "hash": "92c6c16ebb021ab81b6855c7e87cb1913e8bb8b66ec5c6d9d9d8835dd72e394a", "stack_id": "rule_iffj", "alias": ""}, {"content": [["[document]", {"style": "", "class": ""}, 0], ["html", {"style": "", "class": ""}, 0], ["body", {"class": ["home", "blog", "layout-double", "kaztag-news"], "style": ""}, 0], ["div", {"class": ["overflow-container"], "style": ""}, 0], ["div", {"class": ["max-width"], "style": ""}, 0], ["div", {"class": ["content-container"], "style": ""}, 0], ["div", {"class": ["layout-container"], "style": ""}, 0], ["section", {"class": ["main"], "style": ""}, 0], ["div", {"class": ["loop-container", "big-image-block"], "style": ""}, 0], ["div", {"class": ["post", "type-post", "double"], "style": ""}, 0], ["article", {"style": "", "class": ""}, 0], ["div", {"class": ["featured-image"], "style": ""}, 0], ["a", {"style": "", "class": ""}]], "wanted_attr": "href", "is_full_url": true, "is_non_rec_text": null, "url": "https://kaztag.kz/en/news/?PAGEN_1=1", "hash": "89b253431b29af39731831773cf0a439f9e7ecb5f0a54640b9c9245b4aa121e7", "stack_id": "rule_dph1", "alias": ""}, {"content": [["[document]", {"style": "", "class": ""}, 0], ["html", {"style": "", "class": ""}, 0], ["body", {"class": ["home", "blog", "layout-double", "kaztag-news"], "style": ""}, 0], ["div", {"class": ["overflow-container"], "style": ""}, 0], ["div", {"class": ["max-width"], "style": ""}, 0], ["div", {"class": ["content-container"], "style": ""}, 0], ["div", {"class": ["layout-container"], "style": ""}, 0], ["section", {"class": ["main"], "style": ""}, 0], ["div", {"class": ["loop-container", "big-image-block"], "style": ""}, 5], ["div", {"class": ["post", "type-post", "double"], "style": ""}, 0], ["article", {"style": "", "class": ""}, 0], ["div", {"class": ["post-header"], "style": ""}, 0], ["meta", {"style": "", "class": ""}]], "wanted_attr": "content", "is_full_url": null, "is_non_rec_text": null, "url": "", "hash": "cfcc1a17518685d6bfe34e9a86738c4dd1432a499d25e3106e7bf5f71eb9554f", "stack_id": "rule_geam", "alias": ""}, {"content": [["[document]", {"style": "", "class": ""}, 0], ["html", {"style": "", "class": ""}, 0], ["body", {"class": ["home", "blog", "layout-double", "kaztag-news"], "style": ""}, 0], ["div", {"class": ["overflow-container"], "style": ""}, 0], ["div", {"class": ["max-width"], "style": ""}, 0], ["div", {"class": ["content-container"], "style": ""}, 0], ["div", {"class": ["layout-container"], "style": ""}, 0], ["section", {"class": ["main"], "style": ""}, 0], ["div", {"class": ["loop-container", "big-image-block"], "style": ""}, 5], ["div", {"class": ["post", "type-post", "double"], "style": ""}, 0], ["article", {"style": "", "class": ""}, 0], ["div", {"class": ["post-header"], "style": ""}, 0], ["h3", {"class": ["post-title"], "style": ""}]], "wanted_attr": null, "is_full_url": null, "is_non_rec_text": null, "url": "", "hash": "c82d7702f01cdd47555f355edc8ac4595cf4571a9e73155374d3ccc9a18111a4", "stack_id": "rule_bcq4", "alias": ""}, {"content": [["[document]", {"style": "", "class": ""}, 0], ["html", {"style": "", "class": ""}, 0], ["body", {"class": ["home", "blog", "layout-double", "kaztag-news"], "style": ""}, 0], ["div", {"class": ["overflow-container"], "style": ""}, 0], ["div", {"class": ["max-width"], "style": ""}, 0], ["div", {"class": ["content-container"], "style": ""}, 0], ["div", {"class": ["layout-container"], "style": ""}, 0], ["section", {"class": ["main"], "style": ""}, 0], ["div", {"class": ["loop-container", "big-image-block"], "style": ""}, 5], ["div", {"class": ["post", "type-post", "double"], "style": ""}, 0], ["article", {"style": "", "class": ""}, 0], ["div", {"class": ["featured-image"], "style": ""}, 0], ["a", {"style": "", "class": ""}, 0], ["img", {"class": ["attachment-medium", "size-medium"], "style": ""}]], "wanted_attr": "alt", "is_full_url": null, "is_non_rec_text": null, "url": "", "hash": "09b410d2c81565549ef922967b1a31b7dbdadfb3c05b96e0c51e305e2e718c55", "stack_id": "rule_6r60", "alias": ""}, {"content": [["[document]", {"style": "", "class": ""}, 0], ["html", {"style": "", "class": ""}, 0], ["body", {"class": ["home", "blog", "layout-double", "kaztag-news"], "style": ""}, 0], ["div", {"class": ["overflow-container"], "style": ""}, 0], ["div", {"class": ["max-width"], "style": ""}, 0], ["div", {"class": ["content-container"], "style": ""}, 0], ["div", {"class": ["layout-container"], "style": ""}, 0], ["section", {"class": ["main"], "style": ""}, 0], ["div", {"class": ["loop-container", "big-image-block"], "style": ""}, 5], ["div", {"class": ["post", "type-post", "double"], "style": ""}, 0], ["article", {"style": "", "class": ""}, 0], ["div", {"class": ["featured-image"], "style": ""}]], "wanted_attr": null, "is_full_url": null, "is_non_rec_text": null, "url": "", "hash": "6beec23d4a8820e549a3f432421eafb05f92e1bc7e40043fdabffc17e0cfb56b", "stack_id": "rule_w3nt", "alias": ""}, {"content": [["[document]", {"style": "", "class": ""}, 0], ["html", {"style": "", "class": ""}, 0], ["body", {"class": ["home", "blog", "layout-double", "kaztag-news"], "style": ""}, 0], ["div", {"class": ["overflow-container"], "style": ""}, 0], ["div", {"class": ["max-width"], "style": ""}, 0], ["div", {"class": ["content-container"], "style": ""}, 0], ["div", {"class": ["layout-container"], "style": ""}, 0], ["section", {"class": ["main"], "style": ""}, 0], ["div", {"class": ["loop-container", "big-image-block"], "style": ""}, 5], ["div", {"class": ["post", "type-post", "double"], "style": ""}, 0], ["article", {"style": "", "class": ""}, 0], ["div", {"class": ["post-header"], "style": ""}, 0], ["div", {"class": ["post-byline"], "style": ""}]], "wanted_attr": null, "is_full_url": null, "is_non_rec_text": null, "url": "", "hash": "e7f76113100b89002d5866e267829e607332ab9ba646a25a553152f924f8c579", "stack_id": "rule_ojjr", "alias": ""}, {"content": [["[document]", {"style": "", "class": ""}, 0], ["html", {"style": "", "class": ""}, 0], ["body", {"class": ["home", "blog", "layout-double", "kaztag-news"], "style": ""}, 0], ["div", {"class": ["overflow-container"], "style": ""}, 0], ["div", {"class": ["max-width"], "style": ""}, 0], ["div", {"class": ["content-container"], "style": ""}, 0], ["div", {"class": ["layout-container"], "style": ""}, 0], ["section", {"class": ["main"], "style": ""}, 0], ["div", {"class": ["loop-container", "big-image-block"], "style": ""}, 5], ["div", {"class": ["post", "type-post", "double"], "style": ""}, 0], ["article", {"style": "", "class": ""}, 0], ["div", {"class": ["post-header"], "style": ""}, 0], ["h3", {"class": ["post-title"], "style": ""}, 0], ["a", {"style": "", "class": ""}]], "wanted_attr": "href", "is_full_url": true, "is_non_rec_text": null, "url": "https://kaztag.kz/en/news/?PAGEN_1=1", "hash": "831e2e0ee9109bb7e7a7efbde5fa3209a62b169abe50f5f5747c10f2ab2cd545", "stack_id": "rule_duqz", "alias": ""}, {"content": [["[document]", {"style": "", "class": ""}, 0], ["html", {"style": "", "class": ""}, 0], ["body", {"class": ["home", "blog", "layout-double", "kaztag-news"], "style": ""}, 0], ["div", {"class": ["overflow-container"], "style": ""}, 0], ["div", {"class": ["max-width"], "style": ""}, 0], ["div", {"class": ["content-container"], "style": ""}, 0], ["div", {"class": ["layout-container"], "style": ""}, 0], ["section", {"class": ["main"], "style": ""}, 0], ["div", {"class": ["loop-container", "big-image-block"], "style": ""}, 5], ["div", {"class": ["post", "type-post", "double"], "style": ""}, 0], ["article", {"style": "", "class": ""}, 0], ["div", {"class": ["featured-image"], "style": ""}, 0], ["a", {"style": "", "class": ""}]], "wanted_attr": "href", "is_full_url": true, "is_non_rec_text": null, "url": "https://kaztag.kz/en/news/?PAGEN_1=1", "hash": "8d1d343a595871e587a5c99db6fe4894956b9603a63dd83ecc2c0e72baee3878", "stack_id": "rule_9ryn", "alias": ""}, {"content": [["[document]", {"style": "", "class": ""}, 0], ["html", {"style": "", "class": ""}, 0], ["body", {"class": ["home", "blog", "layout-double", "kaztag-news"], "style": ""}, 0], ["div", {"class": ["overflow-container"], "style": ""}, 0], ["div", {"class": ["max-width"], "style": ""}, 0], ["div", {"class": ["content-container"], "style": ""}, 0], ["div", {"class": ["layout-container"], "style": ""}, 0], ["section", {"class": ["main"], "style": ""}, 0], ["div", {"class": ["loop-container", "big-image-block"], "style": ""}, 11], ["div", {"class": ["post", "type-post", "double"], "style": ""}, 0], ["article", {"style": "", "class": ""}, 0], ["div", {"class": ["post-header"], "style": ""}, 0], ["meta", {"style": "", "class": ""}]], "wanted_attr": "content", "is_full_url": null, "is_non_rec_text": null, "url": "", "hash": "dafc55c08020c19a73c546d1034893968ebf54c1bb9b992f752c5f2bca44a7ca", "stack_id": "rule_48bg", "alias": ""}, {"content": [["[document]", {"style": "", "class": ""}, 0], ["html", {"style": "", "class": ""}, 0], ["body", {"class": ["home", "blog", "layout-double", "kaztag-news"], "style": ""}, 0], ["div", {"class": ["overflow-container"], "style": ""}, 0], ["div", {"class": ["max-width"], "style": ""}, 0], ["div", {"class": ["content-container"], "style": ""}, 0], ["div", {"class": ["layout-container"], "style": ""}, 0], ["section", {"class": ["main"], "style": ""}, 0], ["div", {"class": ["loop-container", "big-image-block"], "style": ""}, 11], ["div", {"class": ["post", "type-post", "double"], "style": ""}, 0], ["article", {"style": "", "class": ""}, 0], ["div", {"class": ["post-header"], "style": ""}, 0], ["h3", {"class": ["post-title"], "style": ""}]], "wanted_attr": null, "is_full_url": null, "is_non_rec_text": null, "url": "", "hash": "791ee6eeb493e74d779ee20f3406bfd6db4166cd1cf196df5d9083d7d740c92a", "stack_id": "rule_xvpb", "alias": ""}, {"content": [["[document]", {"style": "", "class": ""}, 0], ["html", {"style": "", "class": ""}, 0], ["body", {"class": ["home", "blog", "layout-double", "kaztag-news"], "style": ""}, 0], ["div", {"class": ["overflow-container"], "style": ""}, 0], ["div", {"class": ["max-width"], "style": ""}, 0], ["div", {"class": ["content-container"], "style": ""}, 0], ["div", {"class": ["layout-container"], "style": ""}, 0], ["section", {"class": ["main"], "style": ""}, 0], ["div", {"class": ["loop-container", "big-image-block"], "style": ""}, 11], ["div", {"class": ["post", "type-post", "double"], "style": ""}, 0], ["article", {"style": "", "class": ""}, 0], ["div", {"class": ["featured-image"], "style": ""}, 0], ["a", {"style": "", "class": ""}, 0], ["img", {"class": ["attachment-medium", "size-medium"], "style": ""}]], "wanted_attr": "alt", "is_full_url": null, "is_non_rec_text": null, "url": "", "hash": "e798915685986862653d58f731ca6e95fbd5e419d69a8920a65bf08fac89c4f4", "stack_id": "rule_53cb", "alias": ""}, {"content": [["[document]", {"style": "", "class": ""}, 0], ["html", {"style": "", "class": ""}, 0], ["body", {"class": ["home", "blog", "layout-double", "kaztag-news"], "style": ""}, 0], ["div", {"class": ["overflow-container"], "style": ""}, 0], ["div", {"class": ["max-width"], "style": ""}, 0], ["div", {"class": ["content-container"], "style": ""}, 0], ["div", {"class": ["layout-container"], "style": ""}, 0], ["section", {"class": ["main"], "style": ""}, 0], ["div", {"class": ["loop-container", "big-image-block"], "style": ""}, 11], ["div", {"class": ["post", "type-post", "double"], "style": ""}, 0], ["article", {"style": "", "class": ""}, 0], ["div", {"class": ["featured-image"], "style": ""}]], "wanted_attr": null, "is_full_url": null, "is_non_rec_text": null, "url": "", "hash": "af79045a7686a05c7a40d541dc10ff38eeec0870a3689d8a1aece34b15014fcd", "stack_id": "rule_b1s7", "alias": ""}, {"content": [["[document]", {"style": "", "class": ""}, 0], ["html", {"style": "", "class": ""}, 0], ["body", {"class": ["home", "blog", "layout-double", "kaztag-news"], "style": ""}, 0], ["div", {"class": ["overflow-container"], "style": ""}, 0], ["div", {"class": ["max-width"], "style": ""}, 0], ["div", {"class": ["content-container"], "style": ""}, 0], ["div", {"class": ["layout-container"], "style": ""}, 0], ["section", {"class": ["main"], "style": ""}, 0], ["div", {"class": ["loop-container", "big-image-block"], "style": ""}, 11], ["div", {"class": ["post", "type-post", "double"], "style": ""}, 0], ["article", {"style": "", "class": ""}, 0], ["div", {"class": ["post-header"], "style": ""}, 0], ["div", {"class": ["post-byline"], "style": ""}]], "wanted_attr": null, "is_full_url": null, "is_non_rec_text": null, "url": "", "hash": "a771a486f80b282340e8c9c019a55d7cb3a058b27e62d36804dfc532552fad67", "stack_id": "rule_unue", "alias": ""}, {"content": [["[document]", {"style": "", "class": ""}, 0], ["html", {"style": "", "class": ""}, 0], ["body", {"class": ["home", "blog", "layout-double", "kaztag-news"], "style": ""}, 0], ["div", {"class": ["overflow-container"], "style": ""}, 0], ["div", {"class": ["max-width"], "style": ""}, 0], ["div", {"class": ["content-container"], "style": ""}, 0], ["div", {"class": ["layout-container"], "style": ""}, 0], ["section", {"class": ["main"], "style": ""}, 0], ["div", {"class": ["loop-container", "big-image-block"], "style": ""}, 11], ["div", {"class": ["post", "type-post", "double"], "style": ""}, 0], ["article", {"style": "", "class": ""}, 0], ["div", {"class": ["post-header"], "style": ""}, 0], ["h3", {"class": ["post-title"], "style": ""}, 0], ["a", {"style": "", "class": ""}]], "wanted_attr": "href", "is_full_url": true, "is_non_rec_text": null, "url": "https://kaztag.kz/en/news/?PAGEN_1=1", "hash": "9100148465463257f51d8481f19dc9f901f6c1534760d4c2e38f14979db54c55", "stack_id": "rule_d726", "alias": ""}, {"content": [["[document]", {"style": "", "class": ""}, 0], ["html", {"style": "", "class": ""}, 0], ["body", {"class": ["home", "blog", "layout-double", "kaztag-news"], "style": ""}, 0], ["div", {"class": ["overflow-container"], "style": ""}, 0], ["div", {"class": ["max-width"], "style": ""}, 0], ["div", {"class": ["content-container"], "style": ""}, 0], ["div", {"class": ["layout-container"], "style": ""}, 0], ["section", {"class": ["main"], "style": ""}, 0], ["div", {"class": ["loop-container", "big-image-block"], "style": ""}, 11], ["div", {"class": ["post", "type-post", "double"], "style": ""}, 0], ["article", {"style": "", "class": ""}, 0], ["div", {"class": ["featured-image"], "style": ""}, 0], ["a", {"style": "", "class": ""}]], "wanted_attr": "href", "is_full_url": true, "is_non_rec_text": null, "url": "https://kaztag.kz/en/news/?PAGEN_1=1", "hash": "e9befd47f6d62998e02147ae77b70370d10939f283355b612d1f41d63045a2b7", "stack_id": "rule_melq", "alias": ""}]}